keycardai/__init__.py
keycardai/agents/__init__.py
keycardai/agents/config.py
keycardai/agents/client/__init__.py
keycardai/agents/client/discovery.py
keycardai/agents/client/oauth.py
keycardai/agents/integrations/__init__.py
keycardai/agents/integrations/crewai.py
keycardai/agents/server/__init__.py
keycardai/agents/server/app.py
keycardai/agents/server/delegation.py
keycardai/agents/server/executor.py
keycardai/agents/server/executor_bridge.py
keycardai_agents-0.1.1.dist-info/METADATA
keycardai_agents-0.1.1.dist-info/WHEEL
keycardai_agents-0.1.1.dist-info/RECORD
