Metadata-Version: 2.4
Name: keycardai-agents
Version: 0.1.1
Summary: Framework-agnostic agent service SDK for A2A delegation with Keycard authentication. Supports CrewAI, LangChain, and custom agents.
Author-email: Keycard <support@keycard.ai>
License: MIT
Keywords: agents,ai,authentication,authorization,crewai,delegation,service
Classifier: Development Status :: 3 - Alpha
Classifier: Intended Audience :: Developers
Classifier: License :: OSI Approved :: MIT License
Classifier: Operating System :: OS Independent
Classifier: Programming Language :: Python :: 3
Classifier: Programming Language :: Python :: 3.10
Classifier: Programming Language :: Python :: 3.11
Classifier: Programming Language :: Python :: 3.12
Classifier: Programming Language :: Python :: 3.13
Classifier: Topic :: Scientific/Engineering :: Artificial Intelligence
Classifier: Topic :: Security
Classifier: Topic :: Software Development :: Libraries :: Python Modules
Requires-Python: >=3.10
Requires-Dist: a2a-sdk>=0.3.22
Requires-Dist: authlib>=1.3.0
Requires-Dist: fastapi>=0.115.0
Requires-Dist: httpx>=0.27.2
Requires-Dist: keycardai-mcp>=0.9.0
Requires-Dist: keycardai-oauth>=0.6.0
Requires-Dist: pydantic>=2.11.7
Requires-Dist: uvicorn[standard]>=0.32.0
Provides-Extra: crewai
Requires-Dist: crewai>=0.86.0; extra == 'crewai'
Provides-Extra: dev
Requires-Dist: mypy>=1.14.1; extra == 'dev'
Requires-Dist: ruff>=0.8.6; extra == 'dev'
Provides-Extra: test
Requires-Dist: pytest-asyncio>=1.1.0; extra == 'test'
Requires-Dist: pytest-cov>=6.2.1; extra == 'test'
Requires-Dist: pytest-timeout>=2.3.1; extra == 'test'
Requires-Dist: pytest>=8.4.1; extra == 'test'
